MANIFEST.in
setup.py
masonite/contrib/azure/__init__.py
masonite/contrib/azure/drivers/UploadAzureDriver.py
masonite/contrib/azure/drivers/__init__.py
masonite/contrib/azure/providers/AzureProvider.py
masonite/contrib/azure/providers/__init__.py
masonite_azure_driver.egg-info/PKG-INFO
masonite_azure_driver.egg-info/SOURCES.txt
masonite_azure_driver.egg-info/dependency_links.txt
masonite_azure_driver.egg-info/requires.txt
masonite_azure_driver.egg-info/top_level.txt