Metadata-Version: 1.0
Name: masonite-azure-driver
Version: 0.0.5
Summary: Azure upload driver for the Masonite framework
Home-page: https://github.com/josephmancuso/masonite-azure-driver
Author: Joseph Mancuso
Author-email: idmann509@gmail.com
License: UNKNOWN
Keywords: python web framework,python3,masonite,azure
Platform: UNKNOWN
